{
	"info": {
		"_postman_id": "576ed23f-a49c-4437-9654-132ed12709a0",
		"name": "BTech",
		"schema": "https://schema.getpostman.com/json/collection/v2.1.0/collection.json",
		"_exporter_id": "22881991"
	},
	"item": [
		{
			"name": "projects",
			"item": [
				{
					"name": "create",
					"request": {
						"method": "POST",
						"header": [],
						"body": {
							"mode": "raw",
							"raw": "{\n    \"name\": \"proj01\"\n}",
							"options": {
								"raw": {
									"language": "json"
								}
							}
						},
						"url": {
							"raw": "{{host}}/project/create",
							"host": [
								"{{host}}"
							],
							"path": [
								"project",
								"create"
							]
						}
					},
					"response": []
				},
				{
					"name": "update",
					"request": {
						"method": "PUT",
						"header": [],
						"body": {
							"mode": "raw",
							"raw": "{\n  \"oldName\": \"proj01\",\n  \"newName\": \"A Better Project Name\"\n}\n",
							"options": {
								"raw": {
									"language": "json"
								}
							}
						},
						"url": {
							"raw": "{{host}}/project/update",
							"host": [
								"{{host}}"
							],
							"path": [
								"project",
								"update"
							]
						}
					},
					"response": []
				},
				{
					"name": "getAll",
					"request": {
						"method": "GET",
						"header": [],
						"url": {
							"raw": "{{host}}/project/getAll",
							"host": [
								"{{host}}"
							],
							"path": [
								"project",
								"getAll"
							]
						}
					},
					"response": []
				},
				{
					"name": "del",
					"request": {
						"method": "DELETE",
						"header": [],
						"body": {
							"mode": "raw",
							"raw": "{\n    \"projName\": \"proj01\"\n}",
							"options": {
								"raw": {
									"language": "json"
								}
							}
						},
						"url": {
							"raw": "{{host}}/project/del",
							"host": [
								"{{host}}"
							],
							"path": [
								"project",
								"del"
							]
						}
					},
					"response": []
				}
			],
			"auth": {
				"type": "bearer",
				"bearer": [
					{
						"key": "token",
						"value": "{{token}}",
						"type": "string"
					}
				]
			},
			"event": [
				{
					"listen": "prerequest",
					"script": {
						"type": "text/javascript",
						"exec": [
							""
						]
					}
				},
				{
					"listen": "test",
					"script": {
						"type": "text/javascript",
						"exec": [
							""
						]
					}
				}
			]
		},
		{
			"name": "tasks",
			"item": [],
			"auth": {
				"type": "bearer",
				"bearer": [
					{
						"key": "token",
						"value": "{{token}}",
						"type": "string"
					}
				]
			},
			"event": [
				{
					"listen": "prerequest",
					"script": {
						"type": "text/javascript",
						"exec": [
							""
						]
					}
				},
				{
					"listen": "test",
					"script": {
						"type": "text/javascript",
						"exec": [
							""
						]
					}
				}
			]
		},
		{
			"name": "helloWorld",
			"request": {
				"method": "GET",
				"header": [],
				"url": {
					"raw": "{{host}}/",
					"host": [
						"{{host}}"
					],
					"path": [
						""
					]
				}
			},
			"response": []
		},
		{
			"name": "register",
			"request": {
				"method": "POST",
				"header": [],
				"body": {
					"mode": "raw",
					"raw": "{\n    \"name\": \"davincif\",\n    \"birth\": \"1994-02-09\",\n    \"password\": \"xablau\"\n}",
					"options": {
						"raw": {
							"language": "json"
						}
					}
				},
				"url": {
					"raw": "{{host}}/user/register",
					"host": [
						"{{host}}"
					],
					"path": [
						"user",
						"register"
					]
				}
			},
			"response": []
		},
		{
			"name": "Login",
			"event": [
				{
					"listen": "test",
					"script": {
						"exec": [
							"let resp = pm.response.json();",
							"if(!resp.data || !resp.data.jwt) {",
							"    return",
							"}",
							"",
							"let _token = resp.data.jwt",
							"",
							"pm.environment.set(\"token\", pm.globals.set('token', _token));"
						],
						"type": "text/javascript"
					}
				}
			],
			"request": {
				"method": "POST",
				"header": [],
				"body": {
					"mode": "raw",
					"raw": "{\n    \"name\": \"davincif\",\n    \"password\": \"xablau\"\n}",
					"options": {
						"raw": {
							"language": "json"
						}
					}
				},
				"url": {
					"raw": "{{host}}/user/login",
					"host": [
						"{{host}}"
					],
					"path": [
						"user",
						"login"
					]
				}
			},
			"response": []
		},
		{
			"name": "Logout",
			"request": {
				"method": "POST",
				"header": [],
				"body": {
					"mode": "raw",
					"raw": "{\n    \"name\": \"davincif\"\n}",
					"options": {
						"raw": {
							"language": "json"
						}
					}
				},
				"url": {
					"raw": "{{host}}/user/logout",
					"host": [
						"{{host}}"
					],
					"path": [
						"user",
						"logout"
					]
				}
			},
			"response": []
		}
	],
	"variable": [
		{
			"key": "host",
			"value": "localhost:3000"
		}
	]
}